pycuc/__init__.py
pycuc/app.py
pycuc/config/__init__.py
pycuc/config/setting.py
pycuc/docs/__init__.py
pycuc/docs/cuc.py
pycuc/docs/cucx.py
pycuc/docs/refs.py
pycuc/docs/utils.py
pycuc-2.1.0.dist-info/METADATA
pycuc-2.1.0.dist-info/WHEEL
pycuc-2.1.0.dist-info/top_level.txt
pycuc-2.1.0.dist-info/RECORD
